freetutorials_dl/__init__.py
freetutorials_dl/cli.py
freetutorials_dl/course.py
freetutorials_dl/downloader.py
freetutorials_dl-1.1.dist-info/LICENSE
freetutorials_dl-1.1.dist-info/METADATA
freetutorials_dl-1.1.dist-info/WHEEL
freetutorials_dl-1.1.dist-info/entry_points.txt
freetutorials_dl-1.1.dist-info/top_level.txt
freetutorials_dl-1.1.dist-info/RECORD
