Metadata-Version: 2.1
Name: freetutorials-dl
Version: 1.1
Summary: Downloader for freetutorials.ca
Home-page: https://github.com/TimilsinaBimal/freetutorials-dl
Author: Timilsina Bimal
License: MIT
Download-URL: https://github.com/TimilsinaBimal/freetutorials-dl/archive/freetutorials-dlv1.0.tar.gz
Keywords: freetutorialsdl,downloader,freetutorials,fts-dl
Platform: UNKNOWN
Classifier: Natural Language :: English
Classifier: Programming Language :: Python :: 3 :: Only
Classifier: License :: Public Domain
Classifier: Operating System :: OS Independent
Requires-Python: >=3.6
Requires-Dist: youtube-dl
Requires-Dist: requests
Requires-Dist: lxml
Requires-Dist: bs4
Requires-Dist: click
